frigg_worker/presets.yaml
frigg_worker/environment_variables.py
frigg_worker/log_helpers.py
frigg_worker/api.py
frigg_worker/jobs.py
frigg_worker/errors.py
frigg_worker/fetcher.py
frigg_worker/__init__.py
frigg_worker/deployments.py
frigg_worker/cli.py
frigg_worker/builds.py
frigg_worker-3.3.2.dist-info/metadata.json
frigg_worker-3.3.2.dist-info/top_level.txt
frigg_worker-3.3.2.dist-info/entry_points.txt
frigg_worker-3.3.2.dist-info/RECORD
frigg_worker-3.3.2.dist-info/DESCRIPTION.rst
frigg_worker-3.3.2.dist-info/METADATA
frigg_worker-3.3.2.dist-info/WHEEL
