Metadata-Version: 2.0
Name: frigg-worker
Version: 3.3.2
Summary: A worker application that listens to the frigg broker an pick up builds and build them.
Home-page: https://github.com/frigg/frigg-worker
Author: The frigg team
Author-email: hi@frigg.io
License: MIT
Platform: UNKNOWN
Classifier: Development Status :: 4 - Beta
Classifier: Programming Language :: Python :: 3
Requires-Dist: click (==5.1)
Requires-Dist: docker-wrapper (>=1.1,<1.2)
Requires-Dist: frigg-coverage (>=1.1.1,<2.0.0)
Requires-Dist: frigg-settings (>=3.1.1,<4.0.0)
Requires-Dist: pyyaml (==3.11)
Requires-Dist: raven (==5.8.1)
